{
    "title": [
        "Adrianna"
    ],
    "toc": [],
    "h1": [],
    "h2": [
        "Adrianna",
        "Základní informace",
        "Dodatečné informace",
        "Výskyt",
        "Gallery"
    ],
    "h3": [
        "Frakce",
        "Profese",
        "Rasa",
        "Ve hře"
    ],
    "content": [
        "Adrianna\nZákladní informace\nFrakce\nAréna\nProfese\nČarodějka\nDodatečné informace\nRasa\nČlověk\nVýskyt\nVe hře\nZaklínač 2: Vrahové králů\nLady Adrianna byla čarodějka v aréně, kterou si Geralt může najmout jako pomoc v boji za 1000.\n\nV aréně je proto, aby otestovala nová kouzla, která vytvořila speciálně pro účely boje. Domnívá se, že pro zaklínače je výhoda bojovat s ní po boku, ne naopak, a proto si za své služby nechává zaplatit.\n\nGallery"
    ]
}