{
    "title": [
        "Anika"
    ],
    "toc": [],
    "h1": [],
    "h2": [
        "Anika",
        "Informace",
        "Reálný svět"
    ],
    "h3": [
        "Pohlaví",
        "Profese",
        "Výskyt"
    ],
    "content": [
        "Anika\nInformace\nPohlaví\nŽena\nProfese\nAdeptka na Arethuse\nReálný svět\nVýskyt\nZaklínač (seriál od Netflixu)\nAnika byla mladá adeptka, kterou Tissaia přivedla na Arethusu, protože u ní zaznamenala magické schopnosti, když se jí podařilo zachránit tonoucího chlapce myšlenkou.\n\nVarování - Spoiler : Následují zásadní informace o ději, které mohou prozradit příběhové zápletky. about seriál na Netlixu\n\nVe druhé zkoušce čtení mysli byla ve dvojici s Yennefer, která jí měla z očí vyčíst její největší strach. Yennefer si nakonec vymyslela, že se Anika nejvíce bojí hadů, za což byla Tissaiou pokárána.\n\nAnika neuspěla v první opravdové zkoušce chytání blesku. Blesk sice do lahve chytila, ale nedokázala ho udržet a lahev jí explodovala do tváře. Při domnělém druhém pokusu ji Tissaia proměnila v úhoře a Yennefer jí vhodila do jezírka, aby její magická moc posílila štít Arethusy."
    ]
}