{
    "title": [
        "Bílý drak"
    ],
    "toc": [],
    "h1": [],
    "h2": [
        "Bílý drak",
        "Obecné informace",
        "Vzhled",
        "Zmínky"
    ],
    "h3": [
        "Klasifikace",
        "Dorozumívání",
        "Výskyt",
        "Schopnosti",
        "Barva kůže",
        "Knihy",
        "Známí bílí draci"
    ],
    "content": [
        "Bílý drak\nObecné informace\nKlasifikace\nDrak\nDorozumívání\nTelepatie\nVýskyt\nDaleký Sever\nSchopnosti\nMrazivý dech\nVzhled\nBarva kůže\nSvětle šedá až namodrale bílá\nZmínky\nKnihy\nMeč osudu\nBílý drak je vzácným poddruhem draků, nejspíše se nachází na dalekém Severu. Průměrná délka bílého draka činí 10 metrů a tento druh chrlí štípavý mráz, který zmrazí vše v blízkosti několika desítek metrů.\n\nObyvatelé Severních království je znají pouze z doslechu a příběhů hrstky odvážných dobrodruhů, kteří je popisují jako obrovská monstra se šupinami barvy světle šedé až po namodrale bílou.\n\nZnámí bílí draci\nGerminus"
    ]
}