{
    "title": [
        "Bruxa"
    ],
    "toc": [],
    "h1": [],
    "h2": [
        "Zápisy do Deníku",
        "Zdroje",
        "Gallery"
    ],
    "h3": [],
    "content": [
        "Skeč Bruxy\n\nBruxa – tzv. vyšší upír, nabývá podoby ženy nebo obřího netopýra.\n\nPoměrné inteligentní, v boji dokáže používat drápy i ostré tesáky, které pak používá k sání krve (ta není pro vyšší úpíry životně důležitá, je to spíš takový 'alkohol', či droga) a také dokáže vyvolat zvukovou vlnu, kterou omračuje protivníky.\n\nDokáže se proměnit v černého ptáka nebo netopýra. U některých brux byla zaznamenána slabá telepatická síla.\n\nZápisy do Deníku\n\tŘíká se, že bruxy v noci loví hezké mladé muže a vysávají jim krev. Tato upírka se v temnotách pohybuje bez sebemenšího šelestu jako kočka a objevuje se u své oběti znenadání. Bruxa může vypadat jako krásná dívka, díky čemuž je možné splést si ji s rusalkou, vždy ji však zradí dlouhé tesáky a neukojitelná chuť na krev.\nVýskyt: Bruxy si pro svá hnízda vybírají ruiny a opuštěná lidská stavení, výjimečně také jeskyně.\nOdolnosti: Jsou odolné vůči strachu a vůči pokusům o omráčení.\nZranitelnost: Citlivost na stříbro a olej proti upírům.\nTaktika: Bruxy útočí ze zálohy, snaží se ovládnout mysl oběti a vysát jí krev.\nAlchymie: Lymfa zrůdnosti a krev bruxy.\n\t\nZdroje\nUpíři: fakty a mýty\nGallery"
    ]
}