{
    "title": [
        "Chiméra (kniha)"
    ],
    "toc": [],
    "h1": [],
    "h2": [
        "Zápisy do Deníku",
        "Cena",
        "Lokace"
    ],
    "h3": [],
    "content": [
        "\tThe Frightener\n\n\"Souhrn informaci o vzácném tvoru označovaném jako chiméra.\"\n\nKnížka shrnující informace o chimérách.\n\nZápisy do Deníku\n\nBestiář: Chiméra\nIngredience:\n\nPařát chiméry\nOko chiméry\nCena\n Nákup\tProdej\n50  \t10  \n\n\n\n\nLokace\na crate in the Večeřadlo on the second floor of Kaer Morhen"
    ]
}