{
    "title": [
        "Ďáblova pecka"
    ],
    "toc": [],
    "h1": [],
    "h2": [
        "Zdroje",
        "Poznámky"
    ],
    "h3": [],
    "content": [
        "Ďáblova pecka – Recepturu ďáblovy pecky vytvořili zerrikánští alchymisté. Díky kupcům se pak dostala do severních království.\n\nÚčinek: Detonace petardy rozptyluje na krátkou vzdálenost slabý jed. Bytosti vůči jedu odolné nemusí být účinkem zasaženy.\n\nPříprava\tZáklad\n\n\n\t\n\n\t\n\n\t\n\nĎáblova pecka se vyrábí smícháním ingrediencí, které dohromady obsahují: jednu dávku rebisu a hydragena a dvě dávky aetheru.\n\n\tprach\nZdroje\nTajemství mistrů jihu\nServírka v Novém Narakortu, pokud se vás zeptá na vaši opilost\nPoznámky\nTuto petardu potřebujete, pokud chcete zabít královnu kikimor, která je zranitelná téměř pouze jedem (funguje na ni např. také znamení Yrden)."
    ]
}