{
    "title": [
        "Marilka"
    ],
    "toc": [],
    "h1": [],
    "h2": [
        "Marilka",
        "Vztahy",
        "Reálný svět"
    ],
    "h3": [
        "Rodiče",
        "Příbuzný",
        "Herec"
    ],
    "content": [
        "\t\t\t\nŽivotopis\tNetflix\t\t\n\n\n\n\nMarilka\nVztahy\nRodiče\nCaldemeyn (otec)\n\nLibuše (matka)\n\nPříbuzný\nAnnika (sestra)\nReálný svět\nHerec\nMia McKenna-Bruce\n\nMarilka je starší dcerou Blavikenského starosty Caldemeyna a jeho ženy Libuše, rovněž má mladší sestru Anniku. Objevuje se v povídce Menší zlo."
    ]
}