{
    "title": [
        "Oleje"
    ],
    "toc": [],
    "h1": [],
    "h2": [
        "Nátěry na meč"
    ],
    "h3": [],
    "content": [
        "Oleje neboli nátěry na meč jsou významnými vylepšeními bojových vlastností zaklínačských mečů. Jejich efekty se různí, některé jsou určené pro boj s určitými typy nepřátel, jiné vyvolávají určitý užitečný efekt. Na čepeli meče vydrží okolo 24 hodin.\nK jejich přípravě je nutný nějaký tuk, čím lepší kvality, tím lépe pro jeho využití v alchymii.\n\n\t\t\tNákup\tProdej\n\tHusí sádlo\tPojme až 4 ingredience\t20 \t4 \n\tLůj\tPojme až 4 ingredience\t20 \t4 \n\tPsí sádlo\tPojme až 5 ingrediencí\t10 \t2 \n\tMedvědí sádlo\tPojme až 5 ingrediencí\t40 \t8 \n\tAlchymistická pasta\tPojme až 5 ingrediencí\t70 \t14 \n\n\n\n\nNátěry na meč\n\n Vitriol  Aether  Rebis  Quebrith  Hydragenum  Vermilion\n\nIkona\tOlej\tSložení\tÚčinky\n\tOlej proti přeludům\t  \tO 100% zvyšuje zranění způsobovaná přeludům (např. barghestům, polednicím, atd.)\n\tOlej proti nekrofágům\t  \tO 100% zvyšuje zranění způsobovaná nekrofágům (např. ghúlům a utopencům)\n\tOlej proti ornitosaurům\t   \tO 100% zvyšuje zranění způsobovaná ornitosaurům (např. wyvernám nebo kuroliškům)\n\tOlej proti insektoidům\t   \tO 100% zvyšuje zranění způsobovaná insectoidům (kikimory, skolopendromorfové, atd.)\n\tOlej proti upírům\t    \tO 100% zvyšuje zranění způsobovaná všem druhům upírů\n\tJed oběšencův\t    \tSilný jed, způsobuje otravu; vhodný zejména proti lidem\n\tCrinfridský olej\t    \tZpůsobuje silnou bolest; vhodný zejména proti lidem\n\tHnědý olej\t    \tSnižuje srážlivost krve; způsobuje krvácení, vhodný zejména proti lidem\n\tArgentia\t    \tZvyšuje o 60% efektivitu stříbrného meče, ocelový pouze otupuje\n\nDalší vylepšení meče viz: Brousky a runové kameny"
    ]
}