{
    "title": [
        "Řád bílé růže"
    ],
    "toc": [],
    "h1": [],
    "h2": [
        "Známí členové řádu",
        "Velmistři řádu"
    ],
    "h3": [],
    "content": [
        "Bílá růže - znak řádu\n\nŘád bílé růže je v Sapkowskiho knihách rytířský řád z království Temerie. V jeho čele stojí autority z řádové kapituly, které předsedá řádový velmistr. Před válkami s Nilfgaardem bylo hlavním posláním řádu šíření víry kultu Věčného ohně, proto nebylo nic neobvyklého, že se rytíři dávali do služeb různých vládců Severních království, včetně ellanderského vévody Herewarda.\n\nRytíři přes sebe nosí karmínové pláště se znakem bílé růže na levém rameni. Zapínají je sponami, taktéž ve tvaru řádového odznaku. Ve výzbroji mají jednoduché neuzavřené přilbice a drátěné kukly a košile chránící krk a trup.\n\nPodle počítačové hry Zaklínač se rozpadající zbytky rytířstva bílé růže pod velením charismatického Jakuba z Aldersbergu po válce s Nilfgaardem  staly základem pro vznik nového rytířského řádu – Řádu planoucí růže.\n\nFalwick a Tailles\n\nZnámí členové řádu\n\nFalwick\nTailles\nRudolf Valaris\nJakub z Aldersbergu\n\nVelmistři řádu\n\nRudolf Valaris\nJakub z Aldersbergu "
    ]
}