{
    "title": [
        "Reginald"
    ],
    "toc": [],
    "h1": [],
    "h2": [
        "Reginald",
        "Základní informace",
        "Dodatečné informace",
        "Vztahy",
        "Výskyt",
        "Život"
    ],
    "h3": [
        "Titul",
        "Přezdívka",
        "Rasa",
        "Národnost",
        "Partner/ka",
        "Potomci",
        "Ve hře",
        "V knize",
        "Osobnost"
    ],
    "content": [
        "Reginald\nZákladní informace\nTitul\nKrál Lyrie\n\nKrál Rivie\nKrál Lyrie a Rivie\n\nPřezdívka\nOdvážný\nDodatečné informace\nRasa\nČlověk\nNárodnost\n Rivie\nVztahy\nPartner/ka\nMeve\nPotomci\nVillem\n\nAnséis\n\nVýskyt\nVe hře\nThronebreakers\nV knize\nKrev elfů\n\nReginald, známý jako Reginald Odvážný, byl rivijským králem od roku 1249 až do své smrti. Rovněž se jednalo o manžela známé královny Meve, díky sňatku se tak později stal i lyrijským králem a země se spojily do království Lyrie a Rivie. Z jejich manželství vzešli dva synové Villem a Anséise.\n\nŽivot\n\nReginald byl korunován králem Rivie roku 1249 a byl jím až do své smrti roku 1259. Ačkoli Meve velice miloval a zplodil s ní dva syny, byl znám pro své mnohé avantýry s jejími dvorními dámami. Ve stejné době, kdy se Reginald oženil s Meve, potkal rovněž svého budoucího rádce a generála Reynarda Odu, kterého zachránil před trestem smrti. Po dvou letech sňatku se mu narodil syn Villem a poté Anséis.\n\nReginald velmi tvrdě jednal se zrádci, to dokázal v roce 1258, kdy se proti němu obrátila rodina Brossardových. Nařídil zabít všechny jejich členy a jejich těla i hroby zničit. Jediný, kdo tehdy unikl jejich hněvu, byl osmiletý Gascon.\n\nNa smrtelné posteli přiznal své ženě, že jediný člověk, na kterého se mohl vždy spolehnout, je Raynard Odo. Jeho nástupkyní se stala ovdovělá Meve.\n\nOsobnost\n\nPřestože svoji ženu velmi miloval, nedokázal odolat pokušení a byl jí mnohokrát nevěrný s jejími dvorními dámami.  \n\nByl velice hloupý, král Vizimir II. z Redanie dokonce tvrdil, že již nemůže být nikoho hloupějšího než Reginalda, že je to prostě nemožné. Hloupost podle všeho zdědili po svém otci i Villem s Anséisem. Avšak, Reginald uměl rozpoznat moudrost v ostatních, a tak se často řídil jejich radami. Zvláště si cenil rad své ženy Meve, kterou respektoval a bral ji jako spoluvládkyni. Uměl přijmout kritiku a v případě nutnosti i ohnout hřbet. \n\nPředchůdce:\n???\t\tKrál Rivie\t\tNástupce:\nMeve\nPředchůdce:\n???\t\tKrál Lyrie\t\tNástupce:\nMeve"
    ]
}