{
    "title": [
        "Shani"
    ],
    "toc": [
        "Obsah\n1\tSága o Zaklínači\n2\tZaklínač\n2.1\tSouvisející úkoly\n2.2\tZápisy do Deníku:\n3\tGalerie"
    ],
    "h1": [],
    "h2": [
        "Shani",
        "Informace",
        "Vztahy",
        "Reálný svět",
        "Obsah",
        "Sága o Zaklínači",
        "Zaklínač",
        "Galerie"
    ],
    "h3": [
        "Profese",
        "Rodiče",
        "Výskyt",
        "Související úkoly",
        "Zápisy do Deníku:"
    ],
    "content": [
        "Následující článek potřebuje ještě hodně práce, aby byl kompletní! Stejně tak mnoho dalších článku.\n\nPokud víte něco o tomto článku či o nějakém jiném více než je již napsáno, neváhejte a editujte. Nevíte jak správně editovat příspěvky a potřebujete poradit? Navštivte detailně zpracovaný manuál, který vás provede základy.\n\n\n\n\nShani\nShani ve datadisku Srdce z kamene\nInformace\nProfese\nMedička\nVztahy\nRodiče\nShanina matka (zmíněna v datadisku Srdce z kamene)\nReálný svět\nVýskyt\nSága o Zaklínači\nZaklínač\nSrdce z kamene (datadisk k Zaklínač 3: Divoký hon)\nShani je původně medička na univerzitě v Oxenfurtu, přítelkyně barda Marigolda a posléze i zaklínače Geralta, účastnila se jako ošetřovatelka bitvy u Brenny a v pozdějším věku se stala děkankou lékařské fakulty univerzity v Oxenfurtu. Později si dokonce otevřela v Oxenfurtu soukromou léčebnu.\n\nObjevuje se nejen v sáze o Zaklínači, ale rovněž v počítačové hře Zaklínač a později i v datadisku zvaném Srdce z kamene pro třetí díl.\n\nObsah\n1\tSága o Zaklínači\n2\tZaklínač\n2.1\tSouvisející úkoly\n2.2\tZápisy do Deníku:\n3\tGalerie\nSága o Zaklínači\n\nShani se poprvé objevuje v knize Krev elfů ve které se seznamuje se zaklínačem Geraltem. Byl to právě Marigold kdo je seznámil.\n\nZaklínač\n\nShani se poprvé objevuje ve Staré Wyzimě, kde Geralt z Rivie, že se i Shani snaží dostat do města, aby mohla svými znalostmi pomoci při ošetřování nakažených morem. Uvnitř města žije společně se starou ženou, která jí dělá domácí a značně ztrpčuje život Shaniným případným hostům.\n\nPozději Geraltovi pomůže provést pitvu jednoho z vězňů, přímo v lazaretu v němž vypomáhala nakaženým.\n\nGeralt přivede Avlina k Shani:\n\nPakliže se Geralt rozhodne svěřit malého Alvina do opatrovnictví medičky, dojde k prohloubení jejich vzájemného vztahu a vždy zaklínače velmi ráda uvidí ve svém příbytku.\n\nGeralt přivede Alvina k Triss:\n\nPakliže se Geralt rozhodne svěřit malého Alvina do opatrovnictví Triss, dojde naopak k narušení vzájemného vztahu, Shani se urazí a odmítne se s Geraltem více bavit. Teprve až později, když vypuknou ve městě nepokoje s Geraltem opět promluví.\n\nJakmile ve městě vypuknou nepokoje, Shani zřídí polní ošetřovnu ve které společně se svými sestrami ošetřuje každého bez ohledu na rasu.\n\nSouvisející úkoly\nAlvin\nAnatomie zločinu\nChuť pomsty\nHořící naděje\nLedové zrcadlo\nLidé a nestvůry\nPaměť meče\nPod ohnivým nebem\nPřítelkyně ze starých časů\nSalamandří ocas\nSkryté skutečnosti\nZřídlo\nZápisy do Deníku:\n\tKrátce pro příchodu do podhradí jsem se za dramatických okolností setkal se Shani, svou známou z dřívější doby. Je naprosto oddaná medicíně, své vášni, a v podhradí měla plné ruce práce, takže na hovory nebyl moc čas. Mám pocit, že mě to zásadové děvče má hodně rádo.\n\nZatáhl jsem Shani do svých potíží se Salamandrou, a ačkoli dívce hrozilo nebezpečí, všechno skončilo dobře. Shani se postarala o své záležitosti v podhradí a vrátila se do Wyzimy, do svého domu v klášterní čtvrti.\n\nShani přes den pracuje v Lebedově špitálu, večer je u sebe doma v klášterní Wyzimě. Nemá ráda, když jí někdo překáží v práci, proto je za ní lepší chodit večer domů.\n\nNa své oslavě Shani vyprávěla o zážitcích z bitvy pod Brennou, kde ošetřovala raněné. Mám pocit, že si mě Shani velmi oblíbila.\n\nRozhodl jsem se předat Alvina do péče Shani. Medička považuje mé rozhodnutí za důkaz důvěry. Dospěla k názoru, že ji mám raději než Triss, což vztah mezi námi posílilo.\n\nRozhodl jsem se předat Alvina do péče Triss. Shani dospěla k názoru, že jí nevěřím a vybral jsem si čarodějku. Naštvala se na mě a vypadá to, že náš románek tímto skončil.\n\nMarigold mi donesl dopis od Shani. Shani mě prosí, abych našel zmizelého Alvina. Dopis je plný obav o hocha i o mě, Shani doufá, že se oba vrátíme a společně založíme rodinu.\n\nShani se přesunula do Staré Wyzimy, kde zuří nepokoje. V provizorním lazaretu léčí zraněné obou znepřátelených stran.\n\nV ledových pustinách jsem potkal Shani, tedy její obraz vytvořený z mé mysli. Medička mi při stíhání velmistra pomáhala.\n\nOdpověděl jsem Shani na dopis a vysvětlil jsem jí, co k ní cítím.\n\n\t\nGalerie\nShani Gwent standalone cardart.jpg\nShani tarot karta 1 EU (uncensored) verze"
    ]
}