{
    "title": [
        "Tesáky alpy"
    ],
    "toc": [],
    "h1": [],
    "h2": [
        "Cena",
        "Zdroje",
        "Poznámky"
    ],
    "h3": [],
    "content": [
        "\t\t\n\nTesáky alpy – Získávány z těl alpů.\n\nCena\n Nákup\tProdej\n5  \t5  \n\n\n\n\nZdroje\nUpíři: fakty a mýty\nPoznámky\nAlp remains will not contain these fangs until you have the Alp bestiary entry.\nYou'll need five of these for Tobias Hoffman\nYou'll also need one of these for the dentist's collection"
    ]
}