{
    "title": [
        "Velká kniha minerálů"
    ],
    "toc": [],
    "h1": [],
    "h2": [
        "Zápisy do Deníku",
        "Cena",
        "Lokace"
    ],
    "h3": [],
    "content": [
        "\tVelká kniha minerálů\n\nThe book discusses minerals used in alchemy, including sulfur, Ginatz's Acid, wine stone, Naezan salts, Calcium Equum, phosphorus, powdered pearl, pyrite, Optima Mater, the Fifth Essence, Ducal Water, Albar's Crystals, Lunar Shards and quicksilver solution. The alchemical substances present in these ingredients are also discussed.\n\nThe book provides information on substances found in all minerals which can be purchased from alchemists.\n\nZápisy do Deníku\n\nIngredience:\n\nAlbarovy krystaly\nCalcium equum\nFosfor\nGinatská kyselina\nKnížecí voda\nPátá esence\nMěsíční úlomky\nNaezanské soli\nOptima mater\nPrášková perla\nPyrit\nRoztok rtuti\nSíra\nVinný kámen\nCena\n Nákup\tProdej\n600  \t120  \n\n\n\n\nLokace\nAlchymista v Kupecké čtvrti\nKnihkupec v Kupecké čtvrti\nPoustevník\nStarší druid v druidském hájku"
    ]
}