{
    "title": [
        "Základy patomorfologie"
    ],
    "toc": [],
    "h1": [],
    "h2": [
        "Základy patomorfologie",
        "Informace",
        "Cena",
        "Zápis v deníku"
    ],
    "h3": [
        "Kategorie",
        "Typ",
        "Zdroj",
        "Váha"
    ],
    "content": [
        "Základy patomorfologie\nKniha pojednávající o pitvách\nInformace\nKategorie\nBěžný\nTyp\nKniha\nZdroj\nLze zakoupit od Felicie Cori\nVáha\n0\nCena\n Nákup\tProdej\n1  \t1  \nZáklady patomorfologie je kniha v Zaklínači 2: Vrahové králů.\n\nMůže se stát, že Felicia ji občas nebude mít na prodej.\n\nZápis v deníku\nZáklady patomorfologie\nMilo Vanderbeck\nSvět by měl konečně pochopit, že prozkoumávání mrtvých může zachránit živé. Jistě, mrtví si zaslouží naši úctu, a to je přesně důvod, proč by podobná zkoumání měli provádět pouze lékaři nebo studenti pod pečlivým dozorem svých profesorů. V dalších částech této práce popisuji, jak nejlépe provádět pitvu a jaké nástroje je vhodné použít k dosažení pravdy při současném zachování úcty k zesnulému."
    ]
}